meapi_python/__init__.py
meapi_python-0.0.1.dist-info/METADATA
meapi_python-0.0.1.dist-info/WHEEL
meapi_python-0.0.1.dist-info/top_level.txt
meapi_python-0.0.1.dist-info/RECORD
