Metadata-Version: 2.1
Name: meapi-python
Version: 0.0.1
Summary: MeAPI - Personal Intelligence API (Coming Soon)
Home-page: https://meapi.dev
Author: MeAPI Team
Author-email: dev@meapi.dev
Project-URL: Homepage, https://meapi.dev
Project-URL: Source, https://github.com/getmeapi/meapi
Project-URL: Documentation, https://docs.meapi.dev
Classifier: Development Status :: 1 - Planning
Classifier: Intended Audience :: Developers
Classifier: License :: OSI Approved :: MIT License
Classifier: Programming Language :: Python :: 3
Classifier: Programming Language :: Python :: 3.8
Classifier: Programming Language :: Python :: 3.9
Classifier: Programming Language :: Python :: 3.10
Classifier: Programming Language :: Python :: 3.11
Requires-Python: >=3.8
